{
  "作者": "大话西游2直放站",
  "安全文件名": "大话西游2直放站",
  "记录数": 24,
  "数据": [
    {
      "主播ID": 3600216642303524.0,
      "主播昵称": "大话西游2直放站",
      "抖音号": 27355023346.0,
      "抖音号（原）": 27355023346.0,
      "火山号": null,
      "火山号（原）": 0.0,
      "粉丝数": 2390.0,
      "上次开播时间": "从未开播",
      "签约类型": "普通主播",
      "运营经纪人": "星河计划",
      "招募经纪人": "星河计划",
      "首播时间": "从未开播",
      "入会时间": "2024-10-10",
      "西瓜号": "-",
      "备注": "25村",
      "分成比-直播音浪收益": 50.0,
      "视频个播有效天": 0.0,
      "开播总时长": "0小时0分钟0秒",
      "开播有效时长": "0小时0分钟0秒",
      "涨粉": 22.0,
      "人气峰值": 0.0,
      "feed看播时长": "0小时0分钟0秒",
      "作品数": 2.0,
      "视频播放量": 64047.0,
      "视频点赞量": 532.0,
      "视频评论量": 106.0,
      "feed_acu": 0.0,
      "主播标签": null,
      "数据日期": "20260216",
      "赛道": null,
      "归属": null,
      "抖音UID": null,
      "主页链接": null,
      "地域": null,
      "标签": null,
      "特殊人设": null,
      "建联方式": null,
      "直播有效率": 0.0,
      "feed效率": 0.0,
      "涨粉率": 0.009205020920502092,
      "单作品播放量": 32023.5
    },
    {
      "主播ID": 3600216642303524.0,
      "主播昵称": "大话西游2直放站",
      "抖音号": 27355023346.0,
      "抖音号（原）": 27355023346.0,
      "火山号": null,
      "火山号（原）": 0.0,
      "粉丝数": 2390.0,
      "上次开播时间": "从未开播",
      "签约类型": "普通主播",
      "运营经纪人": "星河计划",
      "招募经纪人": "星河计划",
      "首播时间": "从未开播",
      "入会时间": "2024-10-10",
      "西瓜号": "-",
      "备注": "25村",
      "分成比-直播音浪收益": 50.0,
      "视频个播有效天": 0.0,
      "开播总时长": "0小时0分钟0秒",
      "开播有效时长": "0小时0分钟0秒",
      "涨粉": 29.0,
      "人气峰值": 0.0,
      "feed看播时长": "0小时0分钟0秒",
      "作品数": 1.0,
      "视频播放量": 65773.0,
      "视频点赞量": 578.0,
      "视频评论量": 68.0,
      "feed_acu": 0.0,
      "主播标签": null,
      "数据日期": "20260217",
      "赛道": null,
      "归属": null,
      "抖音UID": null,
      "主页链接": null,
      "地域": null,
      "标签": null,
      "特殊人设": null,
      "建联方式": null,
      "直播有效率": 0.0,
      "feed效率": 0.0,
      "涨粉率": 0.012133891213389121,
      "单作品播放量": 65773.0
    },
    {
      "主播ID": 3600216642303524.0,
      "主播昵称": "大话西游2直放站",
      "抖音号": 27355023346.0,
      "抖音号（原）": 27355023346.0,
      "火山号": null,
      "火山号（原）": 0.0,
      "粉丝数": 2390.0,
      "上次开播时间": "从未开播",
      "签约类型": "普通主播",
      "运营经纪人": "星河计划",
      "招募经纪人": "星河计划",
      "首播时间": "从未开播",
      "入会时间": "2024-10-10",
      "西瓜号": "-",
      "备注": "25村",
      "分成比-直播音浪收益": 50.0,
      "视频个播有效天": 0.0,
      "开播总时长": "0小时0分钟0秒",
      "开播有效时长": "0小时0分钟0秒",
      "涨粉": 28.0,
      "人气峰值": 0.0,
      "feed看播时长": "0小时0分钟0秒",
      "作品数": 1.0,
      "视频播放量": 58368.0,
      "视频点赞量": 460.0,
      "视频评论量": 65.0,
      "feed_acu": 0.0,
      "主播标签": null,
      "数据日期": "20260218",
      "赛道": null,
      "归属": null,
      "抖音UID": null,
      "主页链接": null,
      "地域": null,
      "标签": null,
      "特殊人设": null,
      "建联方式": null,
      "直播有效率": 0.0,
      "feed效率": 0.0,
      "涨粉率": 0.011715481171548118,
      "单作品播放量": 58368.0
    },
    {
      "主播ID": 3600216642303524.0,
      "主播昵称": "大话西游2直放站",
      "抖音号": 27355023346.0,
      "抖音号（原）": 27355023346.0,
      "火山号": null,
      "火山号（原）": 0.0,
      "粉丝数": 2389.0,
      "上次开播时间": "从未开播",
      "签约类型": "普通主播",
      "运营经纪人": "星河计划",
      "招募经纪人": "星河计划",
      "首播时间": "从未开播",
      "入会时间": "2024-10-10",
      "西瓜号": "-",
      "备注": "25村",
      "分成比-直播音浪收益": 50.0,
      "视频个播有效天": 0.0,
      "开播总时长": "0小时0分钟0秒",
      "开播有效时长": "0小时0分钟0秒",
      "涨粉": 28.0,
      "人气峰值": 0.0,
      "feed看播时长": "0小时0分钟0秒",
      "作品数": 1.0,
      "视频播放量": 29774.0,
      "视频点赞量": 375.0,
      "视频评论量": 174.0,
      "feed_acu": 0.0,
      "主播标签": null,
      "数据日期": "20260222",
      "赛道": null,
      "归属": null,
      "抖音UID": null,
      "主页链接": null,
      "地域": null,
      "标签": null,
      "特殊人设": null,
      "建联方式": null,
      "直播有效率": 0.0,
      "feed效率": 0.0,
      "涨粉率": 0.011720385098367517,
      "单作品播放量": 29774.0
    },
    {
      "主播ID": 3600216642303524.0,
      "主播昵称": "大话西游2直放站",
      "抖音号": 27355023346.0,
      "抖音号（原）": 27355023346.0,
      "火山号": null,
      "火山号（原）": 0.0,
      "粉丝数": 2387.0,
      "上次开播时间": "从未开播",
      "签约类型": "普通主播",
      "运营经纪人": "星河计划",
      "招募经纪人": "星河计划",
      "首播时间": "从未开播",
      "入会时间": "2024-10-10",
      "西瓜号": "-",
      "备注": "25村",
      "分成比-直播音浪收益": 50.0,
      "视频个播有效天": 0.0,
      "开播总时长": "0小时0分钟0秒",
      "开播有效时长": "0小时0分钟0秒",
      "涨粉": 54.0,
      "人气峰值": 0.0,
      "feed看播时长": "0小时0分钟0秒",
      "作品数": 2.0,
      "视频播放量": 157089.0,
      "视频点赞量": 918.0,
      "视频评论量": 180.0,
      "feed_acu": 0.0,
      "主播标签": null,
      "数据日期": "20260224",
      "赛道": null,
      "归属": null,
      "抖音UID": null,
      "主页链接": null,
      "地域": null,
      "标签": null,
      "特殊人设": null,
      "建联方式": null,
      "直播有效率": 0.0,
      "feed效率": 0.0,
      "涨粉率": 0.02262253875157101,
      "单作品播放量": 78544.5
    },
    {
      "主播ID": 3600216642303524.0,
      "主播昵称": "大话西游2直放站",
      "抖音号": 27355023346.0,
      "抖音号（原）": 27355023346.0,
      "火山号": null,
      "火山号（原）": 0.0,
      "粉丝数": 2387.0,
      "上次开播时间": "从未开播",
      "签约类型": "普通主播",
      "运营经纪人": "星河计划",
      "招募经纪人": "星河计划",
      "首播时间": "从未开播",
      "入会时间": "2024-10-10",
      "西瓜号": "-",
      "备注": "25村",
      "分成比-直播音浪收益": 50.0,
      "视频个播有效天": 0.0,
      "开播总时长": "0小时0分钟0秒",
      "开播有效时长": "0小时0分钟0秒",
      "涨粉": 42.0,
      "人气峰值": 0.0,
      "feed看播时长": "0小时0分钟0秒",
      "作品数": 1.0,
      "视频播放量": 145560.0,
      "视频点赞量": 722.0,
      "视频评论量": 131.0,
      "feed_acu": 0.0,
      "主播标签": null,
      "数据日期": "20260225",
      "赛道": null,
      "归属": null,
      "抖音UID": null,
      "主页链接": null,
      "地域": null,
      "标签": null,
      "特殊人设": null,
      "建联方式": null,
      "直播有效率": 0.0,
      "feed效率": 0.0,
      "涨粉率": 0.017595307917888565,
      "单作品播放量": 145560.0
    },
    {
      "主播ID": 3600216642303524.0,
      "主播昵称": "大话西游2直放站",
      "抖音号": 27355023346.0,
      "抖音号（原）": 27355023346.0,
      "火山号": null,
      "火山号（原）": 0.0,
      "粉丝数": 2387.0,
      "上次开播时间": "从未开播",
      "签约类型": "普通主播",
      "运营经纪人": "星河计划",
      "招募经纪人": "星河计划",
      "首播时间": "从未开播",
      "入会时间": "2024-10-10",
      "西瓜号": "-",
      "备注": "25村",
      "分成比-直播音浪收益": 50.0,
      "视频个播有效天": 0.0,
      "开播总时长": "0小时0分钟0秒",
      "开播有效时长": "0小时0分钟0秒",
      "涨粉": 14.0,
      "人气峰值": 0.0,
      "feed看播时长": "0小时0分钟0秒",
      "作品数": 1.0,
      "视频播放量": 28336.0,
      "视频点赞量": 157.0,
      "视频评论量": 88.0,
      "feed_acu": 0.0,
      "主播标签": null,
      "数据日期": "20260226",
      "赛道": null,
      "归属": null,
      "抖音UID": null,
      "主页链接": null,
      "地域": null,
      "标签": null,
      "特殊人设": null,
      "建联方式": null,
      "直播有效率": 0.0,
      "feed效率": 0.0,
      "涨粉率": 0.005865102639296188,
      "单作品播放量": 28336.0
    },
    {
      "主播ID": 3600216642303524.0,
      "主播昵称": "大话西游2直放站",
      "抖音号": 27355023346.0,
      "抖音号（原）": 27355023346.0,
      "火山号": null,
      "火山号（原）": 0.0,
      "粉丝数": 2387.0,
      "上次开播时间": "从未开播",
      "签约类型": "普通主播",
      "运营经纪人": "星河计划",
      "招募经纪人": "星河计划",
      "首播时间": "从未开播",
      "入会时间": "2024-10-10",
      "西瓜号": "-",
      "备注": "25村",
      "分成比-直播音浪收益": 50.0,
      "视频个播有效天": 0.0,
      "开播总时长": "0小时0分钟0秒",
      "开播有效时长": "0小时0分钟0秒",
      "涨粉": 18.0,
      "人气峰值": 0.0,
      "feed看播时长": "0小时0分钟0秒",
      "作品数": 1.0,
      "视频播放量": 19114.0,
      "视频点赞量": 136.0,
      "视频评论量": 64.0,
      "feed_acu": 0.0,
      "主播标签": null,
      "数据日期": "20260227",
      "赛道": null,
      "归属": null,
      "抖音UID": null,
      "主页链接": null,
      "地域": null,
      "标签": null,
      "特殊人设": null,
      "建联方式": null,
      "直播有效率": 0.0,
      "feed效率": 0.0,
      "涨粉率": 0.00754084625052367,
      "单作品播放量": 19114.0
    },
    {
      "主播ID": 3600216642303524.0,
      "主播昵称": "大话西游2直放站",
      "抖音号": 27355023346.0,
      "抖音号（原）": 27355023346.0,
      "火山号": null,
      "火山号（原）": 0.0,
      "粉丝数": 2387.0,
      "上次开播时间": "从未开播",
      "签约类型": "普通主播",
      "运营经纪人": "星河计划",
      "招募经纪人": "星河计划",
      "首播时间": "从未开播",
      "入会时间": "2024-10-10",
      "西瓜号": "-",
      "备注": "25村",
      "分成比-直播音浪收益": 50.0,
      "视频个播有效天": 0.0,
      "开播总时长": "0小时0分钟0秒",
      "开播有效时长": "0小时0分钟0秒",
      "涨粉": 18.0,
      "人气峰值": 0.0,
      "feed看播时长": "0小时0分钟0秒",
      "作品数": 4.0,
      "视频播放量": 34249.0,
      "视频点赞量": 410.0,
      "视频评论量": 126.0,
      "feed_acu": 0.0,
      "主播标签": null,
      "数据日期": "20260228",
      "赛道": null,
      "归属": null,
      "抖音UID": null,
      "主页链接": null,
      "地域": null,
      "标签": null,
      "特殊人设": null,
      "建联方式": null,
      "直播有效率": 0.0,
      "feed效率": 0.0,
      "涨粉率": 0.00754084625052367,
      "单作品播放量": 8562.25
    },
    {
      "主播ID": 3600216642303524.0,
      "主播昵称": "大话西游2直放站",
      "抖音号": 27355023346.0,
      "抖音号（原）": 27355023346.0,
      "火山号": null,
      "火山号（原）": 0.0,
      "粉丝数": 2385.0,
      "上次开播时间": "从未开播",
      "签约类型": "普通主播",
      "运营经纪人": "星河计划",
      "招募经纪人": "星河计划",
      "首播时间": "从未开播",
      "入会时间": "2024-10-10",
      "西瓜号": "-",
      "备注": "25村",
      "分成比-直播音浪收益": 50.0,
      "视频个播有效天": 0.0,
      "开播总时长": "0小时0分钟0秒",
      "开播有效时长": "0小时0分钟0秒",
      "涨粉": 20.0,
      "人气峰值": 0.0,
      "feed看播时长": "0小时0分钟0秒",
      "作品数": 0.0,
      "视频播放量": 51976.0,
      "视频点赞量": 320.0,
      "视频评论量": 108.0,
      "feed_acu": 0.0,
      "主播标签": null,
      "数据日期": "20260301",
      "赛道": null,
      "归属": null,
      "抖音UID": null,
      "主页链接": null,
      "地域": null,
      "标签": null,
      "特殊人设": null,
      "建联方式": null,
      "直播有效率": 0.0,
      "feed效率": 0.0,
      "涨粉率": 0.008385744234800839,
      "单作品播放量": 0.0
    },
    {
      "主播ID": 3600216642303524.0,
      "主播昵称": "大话西游2直放站",
      "抖音号": 27355023346.0,
      "抖音号（原）": 27355023346.0,
      "火山号": null,
      "火山号（原）": 0.0,
      "粉丝数": 2385.0,
      "上次开播时间": "从未开播",
      "签约类型": "普通主播",
      "运营经纪人": "星河计划",
      "招募经纪人": "星河计划",
      "首播时间": "从未开播",
      "入会时间": "2024-10-10",
      "西瓜号": "-",
      "备注": "25村",
      "分成比-直播音浪收益": 50.0,
      "视频个播有效天": 0.0,
      "开播总时长": "0小时0分钟0秒",
      "开播有效时长": "0小时0分钟0秒",
      "涨粉": 11.0,
      "人气峰值": 0.0,
      "feed看播时长": "0小时0分钟0秒",
      "作品数": 0.0,
      "视频播放量": 24030.0,
      "视频点赞量": 163.0,
      "视频评论量": 65.0,
      "feed_acu": 0.0,
      "主播标签": null,
      "数据日期": "20260302",
      "赛道": null,
      "归属": null,
      "抖音UID": null,
      "主页链接": null,
      "地域": null,
      "标签": null,
      "特殊人设": null,
      "建联方式": null,
      "直播有效率": 0.0,
      "feed效率": 0.0,
      "涨粉率": 0.004612159329140462,
      "单作品播放量": 0.0
    },
    {
      "主播ID": 3600216642303524.0,
      "主播昵称": "大话西游2直放站",
      "抖音号": 27355023346.0,
      "抖音号（原）": 27355023346.0,
      "火山号": null,
      "火山号（原）": 0.0,
      "粉丝数": 2385.0,
      "上次开播时间": "从未开播",
      "签约类型": "普通主播",
      "运营经纪人": "星河计划",
      "招募经纪人": "星河计划",
      "首播时间": "从未开播",
      "入会时间": "2024-10-10",
      "西瓜号": "-",
      "备注": "25村",
      "分成比-直播音浪收益": 50.0,
      "视频个播有效天": 0.0,
      "开播总时长": "0小时0分钟0秒",
      "开播有效时长": "0小时0分钟0秒",
      "涨粉": 13.0,
      "人气峰值": 0.0,
      "feed看播时长": "0小时0分钟0秒",
      "作品数": 1.0,
      "视频播放量": 41628.0,
      "视频点赞量": 227.0,
      "视频评论量": 74.0,
      "feed_acu": 0.0,
      "主播标签": null,
      "数据日期": "20260303",
      "赛道": null,
      "归属": null,
      "抖音UID": null,
      "主页链接": null,
      "地域": null,
      "标签": null,
      "特殊人设": null,
      "建联方式": null,
      "直播有效率": 0.0,
      "feed效率": 0.0,
      "涨粉率": 0.005450733752620545,
      "单作品播放量": 41628.0
    },
    {
      "主播ID": 3600216642303524.0,
      "主播昵称": "大话西游2直放站",
      "抖音号": 27355023346.0,
      "抖音号（原）": 27355023346.0,
      "火山号": null,
      "火山号（原）": 0.0,
      "粉丝数": 2385.0,
      "上次开播时间": "从未开播",
      "签约类型": "普通主播",
      "运营经纪人": "星河计划",
      "招募经纪人": "星河计划",
      "首播时间": "从未开播",
      "入会时间": "2024-10-10",
      "西瓜号": "-",
      "备注": "25村",
      "分成比-直播音浪收益": 50.0,
      "视频个播有效天": 0.0,
      "开播总时长": "0小时0分钟0秒",
      "开播有效时长": "0小时0分钟0秒",
      "涨粉": 23.0,
      "人气峰值": 0.0,
      "feed看播时长": "0小时0分钟0秒",
      "作品数": 2.0,
      "视频播放量": 65142.0,
      "视频点赞量": 324.0,
      "视频评论量": 77.0,
      "feed_acu": 0.0,
      "主播标签": null,
      "数据日期": "20260304",
      "赛道": null,
      "归属": null,
      "抖音UID": null,
      "主页链接": null,
      "地域": null,
      "标签": null,
      "特殊人设": null,
      "建联方式": null,
      "直播有效率": 0.0,
      "feed效率": 0.0,
      "涨粉率": 0.009643605870020965,
      "单作品播放量": 32571.0
    },
    {
      "主播ID": 3600216642303524.0,
      "主播昵称": "大话西游2直放站",
      "抖音号": 27355023346.0,
      "抖音号（原）": 27355023346.0,
      "火山号": null,
      "火山号（原）": 0.0,
      "粉丝数": 2385.0,
      "上次开播时间": "从未开播",
      "签约类型": "普通主播",
      "运营经纪人": "星河计划",
      "招募经纪人": "星河计划",
      "首播时间": "从未开播",
      "入会时间": "2024-10-10",
      "西瓜号": "-",
      "备注": "25村",
      "分成比-直播音浪收益": 50.0,
      "视频个播有效天": 0.0,
      "开播总时长": "0小时0分钟0秒",
      "开播有效时长": "0小时0分钟0秒",
      "涨粉": 22.0,
      "人气峰值": 0.0,
      "feed看播时长": "0小时0分钟0秒",
      "作品数": 2.0,
      "视频播放量": 38028.0,
      "视频点赞量": 314.0,
      "视频评论量": 112.0,
      "feed_acu": 0.0,
      "主播标签": null,
      "数据日期": "20260305",
      "赛道": null,
      "归属": null,
      "抖音UID": null,
      "主页链接": null,
      "地域": null,
      "标签": null,
      "特殊人设": null,
      "建联方式": null,
      "直播有效率": 0.0,
      "feed效率": 0.0,
      "涨粉率": 0.009224318658280923,
      "单作品播放量": 19014.0
    },
    {
      "主播ID": 3600216642303524.0,
      "主播昵称": "大话西游2直放站",
      "抖音号": 27355023346.0,
      "抖音号（原）": 27355023346.0,
      "火山号": null,
      "火山号（原）": 0.0,
      "粉丝数": 2385.0,
      "上次开播时间": "从未开播",
      "签约类型": "普通主播",
      "运营经纪人": "星河计划",
      "招募经纪人": "星河计划",
      "首播时间": "从未开播",
      "入会时间": "2024-10-10",
      "西瓜号": "-",
      "备注": "25村",
      "分成比-直播音浪收益": 50.0,
      "视频个播有效天": 0.0,
      "开播总时长": "0小时0分钟0秒",
      "开播有效时长": "0小时0分钟0秒",
      "涨粉": 23.0,
      "人气峰值": 0.0,
      "feed看播时长": "0小时0分钟0秒",
      "作品数": 1.0,
      "视频播放量": 36050.0,
      "视频点赞量": 308.0,
      "视频评论量": 126.0,
      "feed_acu": 0.0,
      "主播标签": null,
      "数据日期": "20260306",
      "赛道": null,
      "归属": null,
      "抖音UID": null,
      "主页链接": null,
      "地域": null,
      "标签": null,
      "特殊人设": null,
      "建联方式": null,
      "直播有效率": 0.0,
      "feed效率": 0.0,
      "涨粉率": 0.009643605870020965,
      "单作品播放量": 36050.0
    },
    {
      "主播ID": 3600216642303524.0,
      "主播昵称": "大话西游2直放站",
      "抖音号": 27355023346.0,
      "抖音号（原）": 27355023346.0,
      "火山号": null,
      "火山号（原）": 0.0,
      "粉丝数": 2385.0,
      "上次开播时间": "从未开播",
      "签约类型": "普通主播",
      "运营经纪人": "星河计划",
      "招募经纪人": "星河计划",
      "首播时间": "从未开播",
      "入会时间": "2024-10-10",
      "西瓜号": "-",
      "备注": "25村",
      "分成比-直播音浪收益": 50.0,
      "视频个播有效天": 0.0,
      "开播总时长": "0小时0分钟0秒",
      "开播有效时长": "0小时0分钟0秒",
      "涨粉": 7.0,
      "人气峰值": 0.0,
      "feed看播时长": "0小时0分钟0秒",
      "作品数": 2.0,
      "视频播放量": 12026.0,
      "视频点赞量": 212.0,
      "视频评论量": 94.0,
      "feed_acu": 0.0,
      "主播标签": null,
      "数据日期": "20260307",
      "赛道": null,
      "归属": null,
      "抖音UID": null,
      "主页链接": null,
      "地域": null,
      "标签": null,
      "特殊人设": null,
      "建联方式": null,
      "直播有效率": 0.0,
      "feed效率": 0.0,
      "涨粉率": 0.0029350104821802936,
      "单作品播放量": 6013.0
    },
    {
      "主播ID": 3600216642303524.0,
      "主播昵称": "大话西游2直放站",
      "抖音号": 27355023346.0,
      "抖音号（原）": 27355023346.0,
      "火山号": null,
      "火山号（原）": 0.0,
      "粉丝数": 2385.0,
      "上次开播时间": "从未开播",
      "签约类型": "普通主播",
      "运营经纪人": "星河计划",
      "招募经纪人": "星河计划",
      "首播时间": "从未开播",
      "入会时间": "2024-10-10",
      "西瓜号": "-",
      "备注": "25村",
      "分成比-直播音浪收益": 50.0,
      "视频个播有效天": 0.0,
      "开播总时长": "0小时0分钟0秒",
      "开播有效时长": "0小时0分钟0秒",
      "涨粉": 12.0,
      "人气峰值": 0.0,
      "feed看播时长": "0小时0分钟0秒",
      "作品数": 1.0,
      "视频播放量": 8566.0,
      "视频点赞量": 129.0,
      "视频评论量": 58.0,
      "feed_acu": 0.0,
      "主播标签": null,
      "数据日期": "20260308",
      "赛道": null,
      "归属": null,
      "抖音UID": null,
      "主页链接": null,
      "地域": null,
      "标签": null,
      "特殊人设": null,
      "建联方式": null,
      "直播有效率": 0.0,
      "feed效率": 0.0,
      "涨粉率": 0.005031446540880503,
      "单作品播放量": 8566.0
    },
    {
      "主播ID": 3600216642303524.0,
      "主播昵称": "大话西游2直放站",
      "抖音号": 27355023346.0,
      "抖音号（原）": 27355023346.0,
      "火山号": null,
      "火山号（原）": 0.0,
      "粉丝数": 2380.0,
      "上次开播时间": "从未开播",
      "签约类型": "普通主播",
      "运营经纪人": "星河计划",
      "招募经纪人": "星河计划",
      "首播时间": "从未开播",
      "入会时间": "2024-10-10",
      "西瓜号": "-",
      "备注": "25村",
      "分成比-直播音浪收益": 50.0,
      "视频个播有效天": 0.0,
      "开播总时长": "0小时0分钟0秒",
      "开播有效时长": "0小时0分钟0秒",
      "涨粉": 9.0,
      "人气峰值": 0.0,
      "feed看播时长": "0小时0分钟0秒",
      "作品数": 1.0,
      "视频播放量": 20014.0,
      "视频点赞量": 219.0,
      "视频评论量": 121.0,
      "feed_acu": 0.0,
      "主播标签": null,
      "数据日期": "20260309",
      "赛道": null,
      "归属": null,
      "抖音UID": null,
      "主页链接": null,
      "地域": null,
      "标签": null,
      "特殊人设": null,
      "建联方式": null,
      "直播有效率": 0.0,
      "feed效率": 0.0,
      "涨粉率": 0.003781512605042017,
      "单作品播放量": 20014.0
    },
    {
      "主播ID": 3600216642303524.0,
      "主播昵称": "大话西游2直放站",
      "抖音号": 27355023346.0,
      "抖音号（原）": 27355023346.0,
      "火山号": null,
      "火山号（原）": 0.0,
      "粉丝数": 2385.0,
      "上次开播时间": "从未开播",
      "签约类型": "普通主播",
      "运营经纪人": "星河计划",
      "招募经纪人": "星河计划",
      "首播时间": "从未开播",
      "入会时间": "2024-10-10",
      "西瓜号": "-",
      "备注": "25村",
      "分成比-直播音浪收益": 50.0,
      "视频个播有效天": 0.0,
      "开播总时长": "0小时0分钟0秒",
      "开播有效时长": "0小时0分钟0秒",
      "涨粉": 5.0,
      "人气峰值": 0.0,
      "feed看播时长": "0小时0分钟0秒",
      "作品数": 1.0,
      "视频播放量": 7027.0,
      "视频点赞量": 157.0,
      "视频评论量": 83.0,
      "feed_acu": 0.0,
      "主播标签": null,
      "数据日期": "20260310",
      "赛道": null,
      "归属": null,
      "抖音UID": null,
      "主页链接": null,
      "地域": null,
      "标签": null,
      "特殊人设": null,
      "建联方式": null,
      "直播有效率": 0.0,
      "feed效率": 0.0,
      "涨粉率": 0.0020964360587002098,
      "单作品播放量": 7027.0
    },
    {
      "主播ID": 3600216642303524.0,
      "主播昵称": "大话西游2直放站",
      "抖音号": 27355023346.0,
      "抖音号（原）": 27355023346.0,
      "火山号": null,
      "火山号（原）": 0.0,
      "粉丝数": 2390.0,
      "上次开播时间": "从未开播",
      "签约类型": "普通主播",
      "运营经纪人": "星河计划",
      "招募经纪人": "星河计划",
      "首播时间": "从未开播",
      "入会时间": "2024-10-10",
      "西瓜号": "-",
      "备注": "25村",
      "分成比-直播音浪收益": 50.0,
      "视频个播有效天": 0.0,
      "开播总时长": "0小时0分钟0秒",
      "开播有效时长": "0小时0分钟0秒",
      "涨粉": 8.0,
      "人气峰值": 0.0,
      "feed看播时长": "0小时0分钟0秒",
      "作品数": 2.0,
      "视频播放量": 19636.0,
      "视频点赞量": 158.0,
      "视频评论量": 66.0,
      "feed_acu": 0.0,
      "主播标签": null,
      "数据日期": "20260311",
      "赛道": null,
      "归属": null,
      "抖音UID": null,
      "主页链接": null,
      "地域": null,
      "标签": null,
      "特殊人设": null,
      "建联方式": null,
      "直播有效率": 0.0,
      "feed效率": 0.0,
      "涨粉率": 0.0033472803347280333,
      "单作品播放量": 9818.0
    },
    {
      "主播ID": 3600216642303524.0,
      "主播昵称": "大话西游2直放站",
      "抖音号": 27355023346.0,
      "抖音号（原）": 27355023346.0,
      "火山号": null,
      "火山号（原）": 0.0,
      "粉丝数": 2396.0,
      "上次开播时间": "从未开播",
      "签约类型": "普通主播",
      "运营经纪人": "星河计划",
      "招募经纪人": "星河计划",
      "首播时间": "从未开播",
      "入会时间": "2024-10-10",
      "西瓜号": "-",
      "备注": "25村",
      "分成比-直播音浪收益": 50.0,
      "视频个播有效天": 0.0,
      "开播总时长": "0小时0分钟0秒",
      "开播有效时长": "0小时0分钟0秒",
      "涨粉": 7.0,
      "人气峰值": 0.0,
      "feed看播时长": "0小时0分钟0秒",
      "作品数": 2.0,
      "视频播放量": 17835.0,
      "视频点赞量": 482.0,
      "视频评论量": 103.0,
      "feed_acu": 0.0,
      "主播标签": null,
      "数据日期": "20260312",
      "赛道": null,
      "归属": null,
      "抖音UID": null,
      "主页链接": null,
      "地域": null,
      "标签": null,
      "特殊人设": null,
      "建联方式": null,
      "直播有效率": 0.0,
      "feed效率": 0.0,
      "涨粉率": 0.002921535893155259,
      "单作品播放量": 8917.5
    },
    {
      "主播ID": 3600216642303524.0,
      "主播昵称": "大话西游2直放站",
      "抖音号": 27355023346.0,
      "抖音号（原）": 27355023346.0,
      "火山号": null,
      "火山号（原）": 0.0,
      "粉丝数": 2427.0,
      "上次开播时间": "从未开播",
      "签约类型": "普通主播",
      "运营经纪人": "星河计划",
      "招募经纪人": "星河计划",
      "首播时间": "从未开播",
      "入会时间": "2024-10-10",
      "西瓜号": "-",
      "备注": "25村",
      "分成比-直播音浪收益": 50.0,
      "视频个播有效天": 0.0,
      "开播总时长": "0小时0分钟0秒",
      "开播有效时长": "0小时0分钟0秒",
      "涨粉": 17.0,
      "人气峰值": 0.0,
      "feed看播时长": "0小时0分钟0秒",
      "作品数": 1.0,
      "视频播放量": 137516.0,
      "视频点赞量": 284.0,
      "视频评论量": 45.0,
      "feed_acu": 0.0,
      "主播标签": null,
      "数据日期": "20260313",
      "赛道": null,
      "归属": null,
      "抖音UID": null,
      "主页链接": null,
      "地域": null,
      "标签": null,
      "特殊人设": null,
      "建联方式": null,
      "直播有效率": 0.0,
      "feed效率": 0.0,
      "涨粉率": 0.007004532344458179,
      "单作品播放量": 137516.0
    },
    {
      "主播ID": 3600216642303524.0,
      "主播昵称": "大话西游2直放站",
      "抖音号": 27355023346.0,
      "抖音号（原）": 27355023346.0,
      "火山号": null,
      "火山号（原）": 0.0,
      "粉丝数": 2427.0,
      "上次开播时间": "从未开播",
      "签约类型": "普通主播",
      "运营经纪人": "星河计划",
      "招募经纪人": "星河计划",
      "首播时间": "从未开播",
      "入会时间": "2024-10-10",
      "西瓜号": "-",
      "备注": "25村",
      "分成比-直播音浪收益": 50.0,
      "视频个播有效天": 0.0,
      "开播总时长": "0小时0分钟0秒",
      "开播有效时长": "0小时0分钟0秒",
      "涨粉": 16.0,
      "人气峰值": 0.0,
      "feed看播时长": "0小时0分钟0秒",
      "作品数": 1.0,
      "视频播放量": 94264.0,
      "视频点赞量": 239.0,
      "视频评论量": 49.0,
      "feed_acu": 0.0,
      "主播标签": null,
      "数据日期": "20260314",
      "赛道": null,
      "归属": null,
      "抖音UID": null,
      "主页链接": null,
      "地域": null,
      "标签": null,
      "特殊人设": null,
      "建联方式": null,
      "直播有效率": 0.0,
      "feed效率": 0.0,
      "涨粉率": 0.006592501030078286,
      "单作品播放量": 94264.0
    },
    {
      "主播ID": 3600216642303524.0,
      "主播昵称": "大话西游2直放站",
      "抖音号": 27355023346.0,
      "抖音号（原）": 27355023346.0,
      "火山号": null,
      "火山号（原）": 0.0,
      "粉丝数": 2428.0,
      "上次开播时间": "从未开播",
      "签约类型": "普通主播",
      "运营经纪人": "星河计划",
      "招募经纪人": "星河计划",
      "首播时间": "从未开播",
      "入会时间": "2024-10-10",
      "西瓜号": "-",
      "备注": "25村",
      "分成比-直播音浪收益": 50.0,
      "视频个播有效天": 0.0,
      "开播总时长": "0小时0分钟0秒",
      "开播有效时长": "0小时0分钟0秒",
      "涨粉": 10.0,
      "人气峰值": 0.0,
      "feed看播时长": "0小时0分钟0秒",
      "作品数": 1.0,
      "视频播放量": 13625.0,
      "视频点赞量": 112.0,
      "视频评论量": 40.0,
      "feed_acu": 0.0,
      "主播标签": null,
      "数据日期": "20260315",
      "赛道": null,
      "归属": null,
      "抖音UID": null,
      "主页链接": null,
      "地域": null,
      "标签": null,
      "特殊人设": null,
      "建联方式": null,
      "直播有效率": 0.0,
      "feed效率": 0.0,
      "涨粉率": 0.004118616144975288,
      "单作品播放量": 13625.0
    }
  ]
}